pypathfinder/__init__.pxd
pypathfinder/__init__.py
pypathfinder/utils.py
pypathfinder/Astar/__init__.py
pypathfinder/Astar/i_tools.py
pypathfinder/Astar/tools.py
pypathfinder/Dijkstra/__init__.py
pypathfinder/Dijkstra/i_tools.py
pypathfinder/Dijkstra/tools.py
pypathfinder/fast/__init__.pxd
pypathfinder/fast/__init__.py
pypathfinder/fast/citools.c
pypathfinder/fast/citools.cp37-win_amd64.pyd
pypathfinder/fast/citools.pxd
pypathfinder/fast/citools.pyx
pypathfinder/fast/ctools.c
pypathfinder/fast/ctools.cp37-win_amd64.pyd
pypathfinder/fast/ctools.pxd
pypathfinder/fast/ctools.pyx
pypathfinder-1.2.dist-info/LICENSE
pypathfinder-1.2.dist-info/METADATA
pypathfinder-1.2.dist-info/WHEEL
pypathfinder-1.2.dist-info/top_level.txt
pypathfinder-1.2.dist-info/RECORD
