Metadata-Version: 2.1
Name: pypathfinder
Version: 1.2
Summary: A small example package
Home-page: https://github.com/MrPoisen/Pathfinding/
Author: MrPoisen
Project-URL: Bug Tracker, https://github.com/MrPoisen/Pathfinding/issues
Classifier: Programming Language :: Python :: 3
Classifier: License :: OSI Approved :: MIT License
Classifier: Operating System :: OS Independent
Requires-Python: >=3.6
License-File: LICENSE
